cpu_monitor/__init__.py
cpu_monitor/cpu_info.py
cpu_monitor/graph_maker.py
cpu_monitor/graphic_output.py
cpu_monitor/load.py
cpu_monitor/loader.py
cpu_monitor/stat_per_proc.py
cpu_monitor-0.3.data/scripts/cpu_monitor
cpu_monitor-0.3.dist-info/DESCRIPTION.rst
cpu_monitor-0.3.dist-info/METADATA
cpu_monitor-0.3.dist-info/RECORD
cpu_monitor-0.3.dist-info/WHEEL
cpu_monitor-0.3.dist-info/metadata.json
cpu_monitor-0.3.dist-info/top_level.txt
