Metadata-Version: 2.0
Name: cpu-monitor
Version: 0.3
Summary: Cpu monitoring and burning tool
Home-page: https://github.com/yotabits/cpu_monitor
Author: yotabits
Author-email: tkostas75@gmail.com
License: MIT
Keywords: monitoring cpu
Platform: UNKNOWN
Classifier: Development Status :: 3 - Alpha
Classifier: Intended Audience :: Developers
Classifier: Topic :: Software Development :: Build Tools
Classifier: License :: OSI Approved :: MIT License
Classifier: Programming Language :: Python :: 2.7
Requires-Dist: colorama
Requires-Dist: dash
Requires-Dist: dash-core-components
Requires-Dist: dash-html-components
Requires-Dist: dash-renderer
Requires-Dist: plotly
Requires-Dist: py-cpuinfo
